crap/__init__.py
crap-1.5.dist-info/DESCRIPTION.rst
crap-1.5.dist-info/METADATA
crap-1.5.dist-info/RECORD
crap-1.5.dist-info/WHEEL
crap-1.5.dist-info/metadata.json
crap-1.5.dist-info/top_level.txt
