Metadata-Version: 2.0
Name: crap
Version: 1.5
Summary: Encodes and decodes files in .crap format. This allows one to execute the file in any languge, immediately upon import.
Home-page: UNKNOWN
Author: Nirman Dave
Author-email: nirman@sourcenet.in
License: UNKNOWN
Platform: UNKNOWN
